ejtraderTH/__init__.py
ejtraderTH/ejtraderTH.py
ejtraderTH-1.0.4.dist-info/LICENSE.txt
ejtraderTH-1.0.4.dist-info/METADATA
ejtraderTH-1.0.4.dist-info/WHEEL
ejtraderTH-1.0.4.dist-info/top_level.txt
ejtraderTH-1.0.4.dist-info/RECORD
