Metadata-Version: 2.1
Name: ejtraderTH
Version: 1.0.4
Summary: This tiny little python module is useful for creating multiple threads of any function in seconds.
Home-page: https://ejtraderTH_mt.readthedocs.io/
Download-URL: https://ejtraderTH.com
Author: Emerson Pedroso
Author-email: support@ejtrader.com
License: MIT License
Project-URL: Bug Reports, https://github.com/traderpedroso/ejtraderTH_mt/issues
Project-URL: Source, https://github.com/traderpedroso/ejtraderTH_mt
Project-URL: Documentation, https://ejtraderTH.readthedocs.io/
Keywords: metatrader,f-api,historical-data,financial-data,stocks,funds,etfs,indices,currency crosses,bonds,commodities,crypto currencies
Classifier: Programming Language :: Python :: 3 :: Only
Classifier: Programming Language :: Python :: 3.5
Classifier: Programming Language :: Python :: 3.6
Classifier: Programming Language :: Python :: 3.7
Classifier: Programming Language :: Python :: 3.8
Classifier: License :: OSI Approved :: MIT License
Classifier: Intended Audience :: Developers
Classifier: Topic :: Office/Business :: Financial
Classifier: Topic :: Office/Business :: Financial :: Investment
Classifier: Topic :: Scientific/Engineering :: Information Analysis
Classifier: Topic :: Software Development :: Libraries
Requires-Python: >=3
License-File: LICENSE.txt
